{
  "announcement": {
    "id": "0",
    "en": {
      "title": "",
      "text": ""
    },
    "gr": {
      "title": "",
      "text": ""
    }
  },
  "channels": [
    {
      "name": "ERT 1",
      "category": "gr",
      "type": "m3u",
      "url": "https://ert-live-bcbs15228.siliconweb.com/media/ert_1/ert_1medium.m3u8",
      "icon": "https://greektvapp.github.io/api/logos/ert1.png",
      "epg-id": "ert.ert1.gr"
    },
    {
      "name": "ERT 2",
      "category": "gr",
      "type": "m3u",
      "url": "https://ert-live-bcbs15228.siliconweb.com/media/ert_2/ert_2medium.m3u8",
      "icon": "https://greektvapp.github.io/api/logos/ert2.png",
      "epg-id": "ert/ert2.gr"
    }
  ]
}
